PD1/final_submission2/memory_testbench.v
`define mem_size 1048576 //Bytes
`define source "SumArray.x" //Binary file to load Memory from
`define start_address 32'h01000000

module memory(
    input clk,
    input [31:0] address,
    input [31:0] data_in,
    input w_enable,
    output [31:0] data_out
);

reg [31:0]data_out;
reg [7:0]mem[`start_address:`start_address + (`mem_size-1)];

//setup vars
integer i;
reg [31:0]t_mem[0:(`mem_size/4)-1];
reg [31:0]t_reg;

initial begin

    $display("memorySize=%d", `mem_size);
    for (i=0;i<=`mem_size;i=i+1) begin
                t_mem[i] = 0;
    end

    $display("memorySize = %dB", `mem_size);
    $readmemh(`source, t_mem);
    i = 0;

    for (i=0;i<=`mem_size;i=i+1) begin

        t_reg = t_mem[i];
        mem[(4*i)+`start_address] = t_reg[7:0];
        mem[(4*i)+1+`start_address] = t_reg[15:8];
        mem[(4*i)+2+`start_address] = t_reg[23:16];
        mem[(4*i)+3+`start_address] = t_reg[31:24];
    end     


end



        


// Reads Combinational

always @(w_enable, address)
begin
    if(~w_enable) begin
        data_out[7:0] <= mem[address];
        data_out[15:8] <= mem[address + 1];
        data_out[23:16] <= mem[address + 2];
        data_out[31:24] <= mem[address + 3];
    end
end

// Writes Sequential

always@(posedge clk)
begin
    if (w_enable) begin
        mem[address] <= data_in[7:0];
        mem[address + 1] <= data_in[15:8];
        mem[address + 2] <= data_in[23:16];
        mem[address + 3] <= data_in[31:24];

    end
end

endmodule
module dut;

    reg clk = 0;
    reg [31:0] address = `start_address;
    wire [31:0] data_out;
    reg [31:0] data_in = 0;
    reg w_enable = 0;

   

    initial begin


    
        $dumpfile("memory_testbench.vcd");
            // All variables (0) from module instance gate
            $dumpvars(0, mem1);
            $dumpvars(0, dut);
            
            #13 address = address + 4;
            while(data_out != 0) #10 address = address + 4;

           $display("Finished Reading the program");
            #20 data_in = 32'hDEADBEEF;
                w_enable = 1; $display("Driving a write to current address");
            #10 w_enable = 0; $display("Deasserting write");
            #10 address = address + 4;
                data_in = 32'h00000001;
                w_enable = 1;
                #3 data_in = 32'h00000001;
                #3 data_in = 32'h00000002;
                #3 data_in = 32'h00000003;
                #3 data_in = 32'h00000004;
                #3 w_enable = 0;
            #20 $finish;
    end
    

    memory mem1(.clk(clk),.address(address),.data_in(data_in),.w_enable(w_enable),.data_out(data_out));

    always begin
        #5 clk <= ~clk;
    end

    always @(posedge clk) begin
       $display("time=%t address=%x data_out(h)=%x, data_in(h)=%x , w_enable=%b", $time, address,data_out,data_in,w_enable);

    end


endmodule

PD1/final_submission2/memory_testbench.vcd
$date
	Sun May 24 14:16:54 2020
$end
$version
	Icarus Verilog
$end
$timescale
	1s
$end
$scope module dut $end
$scope module mem1 $end
$var wire 32 ! address [31:0] $end
$var wire 1 " clk $end
$var wire 32 # data_in [31:0] $end
$var wire 1 $ w_enable $end
$var reg 32 % data_out [31:0] $end
$var reg 32 & t_reg [31:0] $end
$var integer 32 ' i [31:0] $end
$upscope $end
$upscope $end
$scope module dut $end
$var wire 32 ( data_out [31:0] $end
$var reg 32 ) address [31:0] $end
$var reg 1 " clk $end
$var reg 32 * data_in [31:0] $end
$var reg 1 $ w_enable $end
$scope module mem1 $end
$upscope $end
$upscope $end
$enddefinitions $end
#0
$dumpvars
b0 *
b1000000000000000000000000 )
b11111100000000010000000100010011 (
b100000000000000000001 '
bx &
b11111100000000010000000100010011 %
0$
b0 #
0"
b1000000000000000000000000 !
$end
#5
1"
#10
0"
#13
b10000100010010111000100011 %
b10000100010010111000100011 (
b1000000000000000000000100 !
b1000000000000000000000100 )
#15
1"
#20
0"
#23
b10000000010010011000100011 %
b10000000010010011000100011 (
b1000000000000000000001000 !
b1000000000000000000001000 )
#25
1"
#30
0"
#33
b10000000010010010000100011 %
b10000000010010010000100011 (
b1000000000000000000001100 !
b1000000000000000000001100 )
#35
1"
#40
0"
#43
b10000000010010011000100011 %
b10000000010010011000100011 (
b1000000000000000000010000 !
b1000000000000000000010000 )
#45
1"
#50
0"
#53
b10100000000000000001101111 %
b10100000000000000001101111 (
b1000000000000000000010100 !
b1000000000000000000010100 )
#55
1"
#60
0"
#63
b10110000010010011110000011 %
b10110000010010011110000011 (
b1000000000000000000011000 !
b1000000000000000000011000 )
#65
1"
#70
0"
#73
b1001111001011110010011 %
b1001111001011110010011 (
b1000000000000000000011100 !
b1000000000000000000011100 )
#75
1"
#80
0"
#83
b11000000010000011100010011 %
b11000000010000011100010011 (
b1000000000000000000100000 !
b1000000000000000000100000 )
#85
1"
#90
0"
#93
b111101110000011110110011 %
b111101110000011110110011 (
b1000000000000000000100100 !
b1000000000000000000100100 )
#95
1"
#100
0"
#103
b10110000010010011100000011 %
b10110000010010011100000011 (
b1000000000000000000101000 !
b1000000000000000000101000 )
#105
1"
#110
0"
#113
b11111100111001111010100000100011 %
b11111100111001111010100000100011 (
b1000000000000000000101100 !
b1000000000000000000101100 )
#115
1"
#120
0"
#123
b10110000010010011110000011 %
b10110000010010011110000011 (
b1000000000000000000110000 !
b1000000000000000000110000 )
#125
1"
#130
0"
#133
b101111000011110010011 %
b101111000011110010011 (
b1000000000000000000110100 !
b1000000000000000000110100 )
#135
1"
#140
0"
#143
b10111100010010011000100011 %
b10111100010010011000100011 (
b1000000000000000000111000 !
b1000000000000000000111000 )
#145
1"
#150
0"
#153
b10110000010010011100000011 %
b10110000010010011100000011 (
b1000000000000000000111100 !
b1000000000000000000111100 )
#155
1"
#160
0"
#163
b100100000000011110010011 %
b100100000000011110010011 (
b1000000000000000001000000 !
b1000000000000000001000000 )
#165
1"
#170
0"
#173
b11111100111001111101101011100011 %
b11111100111001111101101011100011 (
b1000000000000000001000100 !
b1000000000000000001000100 )
#175
1"
#180
0"
#183
b10000000010010011000100011 %
b10000000010010011000100011 (
b1000000000000000001001000 !
b1000000000000000001001000 )
#185
1"
#190
0"
#193
b11000000000000000001101111 %
b11000000000000000001101111 (
b1000000000000000001001100 !
b1000000000000000001001100 )
#195
1"
#200
0"
#203
b10110000010010011110000011 %
b10110000010010011110000011 (
b1000000000000000001010000 !
b1000000000000000001010000 )
#205
1"
#210
0"
#213
b1001111001011110010011 %
b1001111001011110010011 (
b1000000000000000001010100 !
b1000000000000000001010100 )
#215
1"
#220
0"
#223
b11000000010000011100010011 %
b11000000010000011100010011 (
b1000000000000000001011000 !
b1000000000000000001011000 )
#225
1"
#230
0"
#233
b111101110000011110110011 %
b111101110000011110110011 (
b1000000000000000001011100 !
b1000000000000000001011100 )
#235
1"
#240
0"
#243
b11111101000001111010011110000011 %
b11111101000001111010011110000011 (
b1000000000000000001100000 !
b1000000000000000001100000 )
#245
1"
#250
0"
#253
b10100000010010011100000011 %
b10100000010010011100000011 (
b1000000000000000001100100 !
b1000000000000000001100100 )
#255
1"
#260
0"
#263
b111101110000011110110011 %
b111101110000011110110011 (
b1000000000000000001101000 !
b1000000000000000001101000 )
#265
1"
#270
0"
#273
b10111100010010010000100011 %
b10111100010010010000100011 (
b1000000000000000001101100 !
b1000000000000000001101100 )
#275
1"
#280
0"
#283
b10110000010010011110000011 %
b10110000010010011110000011 (
b1000000000000000001110000 !
b1000000000000000001110000 )
#285
1"
#290
0"
#293
b101111000011110010011 %
b101111000011110010011 (
b1000000000000000001110100 !
b1000000000000000001110100 )
#295
1"
#300
0"
#303
b10111100010010011000100011 %
b10111100010010011000100011 (
b1000000000000000001111000 !
b1000000000000000001111000 )
#305
1"
#310
0"
#313
b10110000010010011100000011 %
b10110000010010011100000011 (
b1000000000000000001111100 !
b1000000000000000001111100 )
#315
1"
#320
0"
#323
b100100000000011110010011 %
b100100000000011110010011 (
b1000000000000000010000000 !
b1000000000000000010000000 )
#325
1"
#330
0"
#333
b11111100111001111101011011100011 %
b11111100111001111101011011100011 (
b1000000000000000010000100 !
b1000000000000000010000100 )
#335
1"
#340
0"
#343
b10100000010010010100000011 %
b10100000010010010100000011 (
b1000000000000000010001000 !
b1000000000000000010001000 )
#345
1"
#350
0"
#353
b1100000000000000011101111 %
b1100000000000000011101111 (
b1000000000000000010001100 !
b1000000000000000010001100 )
#355
1"
#360
0"
#363
b1010000011110010011 %
b1010000011110010011 (
b1000000000000000010010000 !
b1000000000000000010010000 )
#365
1"
#370
0"
#373
b1111000010100010011 %
b1111000010100010011 (
b1000000000000000010010100 !
b1000000000000000010010100 )
#375
1"
#380
0"
#383
b11110000010010000010000011 %
b11110000010010000010000011 (
b1000000000000000010011000 !
b1000000000000000010011000 )
#385
1"
#390
0"
#393
b100000000010000000100010011 %
b100000000010000000100010011 (
b1000000000000000010011100 !
b1000000000000000010011100 )
#395
1"
#400
0"
#403
b1000000001100111 %
b1000000001100111 (
b1000000000000000010100000 !
b1000000000000000010100000 )
#405
1"
#410
0"
#413
b11111110000000010000000100010011 %
b11111110000000010000000100010011 (
b1000000000000000010100100 !
b1000000000000000010100100 )
#415
1"
#420
0"
#423
b100010010111000100011 %
b100010010111000100011 (
b1000000000000000010101000 !
b1000000000000000010101000 )
#425
1"
#430
0"
#433
b101000010010011000100011 %
b101000010010011000100011 (
b1000000000000000010101100 !
b1000000000000000010101100 )
#435
1"
#440
0"
#443
b110000010010011100000011 %
b110000010010011100000011 (
b1000000000000000010110000 !
b1000000000000000010110000 )
#445
1"
#450
0"
#453
b10110100000000011110010011 %
b10110100000000011110010011 (
b1000000000000000010110100 !
b1000000000000000010110100 )
#455
1"
#460
0"
#463
b111101110001100001100011 %
b111101110001100001100011 (
b1000000000000000010111000 !
b1000000000000000010111000 )
#465
1"
#470
0"
#473
b10010000000000000011101111 %
b10010000000000000011101111 (
b1000000000000000010111100 !
b1000000000000000010111100 )
#475
1"
#480
0"
#483
b1010000011110010011 %
b1010000011110010011 (
b1000000000000000011000000 !
b1000000000000000011000000 )
#485
1"
#490
0"
#493
b110000000000000001101111 %
b110000000000000001101111 (
b1000000000000000011000100 !
b1000000000000000011000100 )
#495
1"
#500
0"
#503
b10010000000000000011101111 %
b10010000000000000011101111 (
b1000000000000000011001000 !
b1000000000000000011001000 )
#505
1"
#510
0"
#513
b1010000011110010011 %
b1010000011110010011 (
b1000000000000000011001100 !
b1000000000000000011001100 )
#515
1"
#520
0"
#523
b1111000010100010011 %
b1111000010100010011 (
b1000000000000000011010000 !
b1000000000000000011010000 )
#525
1"
#530
0"
#533
b1110000010010000010000011 %
b1110000010010000010000011 (
b1000000000000000011010100 !
b1000000000000000011010100 )
#535
1"
#540
0"
#543
b10000000010000000100010011 %
b10000000010000000100010011 (
b1000000000000000011011000 !
b1000000000000000011011000 )
#545
1"
#550
0"
#553
b1000000001100111 %
b1000000001100111 (
b1000000000000000011011100 !
b1000000000000000011011100 )
#555
1"
#560
0"
#563
b100000000011110010011 %
b100000000011110010011 (
b1000000000000000011100000 !
b1000000000000000011100000 )
#565
1"
#570
0"
#573
b1111000010100010011 %
b1111000010100010011 (
b1000000000000000011100100 !
b1000000000000000011100100 )
#575
1"
#580
0"
#583
b1000000001100111 %
b1000000001100111 (
b1000000000000000011101000 !
b1000000000000000011101000 )
#585
1"
#590
0"
#593
b11110010011 %
b11110010011 (
b1000000000000000011101100 !
b1000000000000000011101100 )
#595
1"
#600
0"
#603
b1111000010100010011 %
b1111000010100010011 (
b1000000000000000011110000 !
b1000000000000000011110000 )
#605
1"
#610
0"
#613
b1000000001100111 %
b1000000001100111 (
b1000000000000000011110100 !
b1000000000000000011110100 )
#615
1"
#620
0"
#623
b0 %
b0 (
b1000000000000000011111000 !
b1000000000000000011111000 )
#625
1"
#630
0"
#633
b1000000000000000011111100 !
b1000000000000000011111100 )
#635
1"
#640
0"
#645
1"
#650
0"
#653
1$
b11011110101011011011111011101111 #
b11011110101011011011111011101111 *
#655
1"
#660
0"
#663
b11011110101011011011111011101111 %
b11011110101011011011111011101111 (
0$
#665
1"
#670
0"
#673
1$
b1 #
b1 *
b1000000000000000100000000 !
b1000000000000000100000000 )
#675
1"
#679
b10 #
b10 *
#680
0"
#682
b11 #
b11 *
#685
1"
b100 #
b100 *
#688
b100 %
b100 (
0$
