PD2/constants.v
`define LUI     7'b01101_11      // lui   rd,imm[31:12]
`define AUIPC   7'b00101_11      // auipc rd,imm[31:12]
`define JAL     7'b11011_11      // jal   rd,imm[xxxxx]
`define JALR    7'b11001_11      // jalr  rd,rs1,imm[11:0] 
`define BCC     7'b11000_11      // bcc   rs1,rs2,imm[12:1]
`define LCC     7'b00000_11      // lxx   rd,rs1,imm[11:0]
`define SCC     7'b01000_11      // sxx   rs1,rs2,imm[11:0]
`define MCC     7'b00100_11      // xxxi  rd,rs1,imm[11:0]
`define RCC     7'b01100_11      // xxx   rd,rs1,rs2 
`define FCC     7'b00011_11      // fencex

//FOR CCC, only ident ECALL, not other opcodes
`define CCC     7'b11100_11      // exx, csrxx
//

PD2/fetch_decode.v
//`include "memory.v"
`include "constants.v"
`define TB



module fetch_decode(
    input clk,
    input [31:0]mem_out,

    output [31:0] next_PC,
    output [31:0]instruction,
    output [6:0]opcode,
    output [4:0]rd,
    output [2:0]funct3,
    output [6:0]funct7,
    output [4:0]rs1,
    output [4:0]rs2,
    //shamt is the same thing as rs2, maybe I can just remove shamt and use rs2 in it's place when doing a shift
    output [4:0]shamt,
    output signed [31:0]imm,
    output rs1_en,
    output rs2_en,
    output rd_en,
    output imm_e

     `ifdef TB
        , output [31:0]PC
    `endif
    
);
    
    reg [31:0] instruction;
    wire [31:0] mem_out;
    ///Address of the instruction currently in the instruction register
    reg [31:0]PC;
    //Memory access register is 4 bytes ahead so the memory can access it while we process the current instruction
    reg [31:0]next_PC = 32'h01000000;

    //instruction components

    reg signed [31:0]imm;
    reg rs1_en, rs2_en, rd_en, imm_e;

    // sequential fetching
    always@(posedge clk) begin
        instruction <= mem_out;
        PC <= next_PC;
        //increment the address selector to the memory so the next instruction will be ready to read on the next clk edge
        next_PC <= next_PC + 4;
    end

    // combinational decoding

    assign opcode = instruction[6:0];
    assign rd = instruction[11:7];
    assign funct3 = instruction[14:12];
    assign rs1 = instruction[19:15];
    assign rs2 = instruction[24:20];
    assign funct7 = instruction[31:25];
    assign shamt = instruction[24:20];

    always@(instruction) begin
        // $write("%x:\t %x = %b %b %b %b \t", PC, instruction, instruction[31:24], instruction[23:16], instruction[15:8], instruction[7:0]);
        //$write("%x:\t %x\t", PC, instruction);
        case(opcode)
            `LUI: decode_uType();
            `AUIPC: decode_uType();
            `JAL: decode_jType();
            `JALR: begin
                if (funct3 == 3'b000) decode_iType();
                else $display("Detected Unknown funct3: %0b of Type JALR at PC=%x", funct3, PC);
            end
            `BCC: decode_bType();
            
            `LCC: decode_iType();
                
            `SCC: decode_sType();
            //we will always want to sign extend in MCC opcodes
            `MCC: begin
                //$write("Detected a MCC opcode\n");
                case(funct3)
                    //I-Type cases
                    3'b000, 3'b010, 3'b011,
                    3'b100, 3'b110,
                    3'b111: decode_iType();
                    //R-Type cases
                    3'b001,
                    3'b101: decode_rType();
                    default: $display("Unknown MCC opcode: %b", opcode);
                endcase
                
            end
            `RCC: decode_rType();
            `FCC: $write("Detected a FCC opcode, these are not implemented\n");
            `CCC: begin
                if(instruction[31:7] == 25'd0) begin 
                    $display("ECALL  ");
                    $finish;
                end
                else $display("Looks like ECALL but the bits are wrong: %b", instruction);

            end
            default: $display("malformed/unimplemented opcode (%0b) encountered at %8x ", opcode, PC);
        endcase
        
        

    end

    // Instruction decoder tasks by Type

    // I'm doing sign extension in the decoders, however I think sometimes the immediates are
    // sign extended and sometimes not so maybe need to move sign extension to the case stmnts

    //R-type requires no immediate decoding so we can just use assigns, but we must assert the enables
    task decode_rType;
        begin
            rd_en
     = 1;
            rs1_en = 1;
            rs2_en = 1;
            imm_e = 0;
        end
    endtask

    //12 bit immediate field
    task decode_iType;
        begin
            rd_en
     = 1;
            rs1_en = 1;
            rs2_en = 0;
            imm_e = 1;
            imm[31:12] = {20{instruction[31]}};
            imm[11:0] = instruction[31:20];
        end
    endtask
    //another 12 bit immediate field but split by the rd1 field
    task decode_sType;
        begin
            rd_en
     = 0;
            rs1_en = 1;
            rs2_en = 1;
            imm_e = 1;
            imm[31:12] = {20{instruction[31]}};
            imm[11:5] = instruction[31:25];
            imm[4:0] = instruction[11:7];
        end
    endtask

    //13 bit immediate field
    task decode_bType;
        begin
            rd_en
     = 0;
            rs1_en = 1;
            rs2_en = 1;
            imm_e = 1;
            imm[0] = 1'b0;
            imm[31:13] = {19{instruction[31]}};
            imm[12] = instruction[31];
            imm[11] = instruction[7];
            imm[10:5] = instruction[30:25];
            imm[4:1] = instruction[11:8];
        end
    endtask

    task decode_uType;
        begin
            rd_en
     = 1;
            rs1_en = 0;
            rs2_en = 0;
            imm_e = 1;
            imm[31:12] = instruction[31:12];
            imm[11:0] = 12'd0;
        end
    endtask

    task decode_jType;
        begin
            rd_en
     = 1;
            rs1_en = 0;
            rs2_en = 0;
            imm_e = 1;
            imm[31:21] = {11{instruction[31]}};
            imm[19:12] = instruction[19:12];
            imm[11] = instruction[20];
            imm[10:1] = instruction[30:21];
            imm[20] = instruction[31];
        end
    endtask


endmodule

PD2/memory.v
`define mem_size 1048576 //Bytes
`define source "simple_programs/SumArray.x" //Binary file to load Memory from
`define start_address 32'h01000000

module memory(
    input clk,
    input [31:0] address,
    input [31:0] data_in,
    input w_enable,
    output [31:0] data_out
);

reg [31:0]data_out;
reg [7:0]mem[`start_address:`start_address + (`mem_size-1)];

//setup vars
integer i;
reg [31:0]t_mem[0:(`mem_size/4)-1];
reg [31:0]t_reg;

initial begin

    //$display("memorySize=%d", `mem_size);
    for (i=0;i<=`mem_size;i=i+1) begin
                t_mem[i] = 0;
    end

    //$display("memorySize = %dB", `mem_size);
    $readmemh(`source, t_mem);
    i = 0;

    for (i=0;i<=`mem_size;i=i+1) begin

        t_reg = t_mem[i];
        mem[(4*i)+`start_address] = t_reg[7:0];
        mem[(4*i)+1+`start_address] = t_reg[15:8];
        mem[(4*i)+2+`start_address] = t_reg[23:16];
        mem[(4*i)+3+`start_address] = t_reg[31:24];
    end     


end



        


// Reads Combinational

always @(w_enable, address)
begin
    if(~w_enable) begin
        data_out[7:0] <= mem[address];
        data_out[15:8] <= mem[address + 1];
        data_out[23:16] <= mem[address + 2];
        data_out[31:24] <= mem[address + 3];
    end
    else data_out <= data_out;
end

// Writes Sequential

always@(posedge clk)
begin
    if (w_enable) begin
        mem[address] <= data_in[7:0];
        mem[address + 1] <= data_in[15:8];
        mem[address + 2] <= data_in[23:16];
        mem[address + 3] <= data_in[31:24];

    end
end

endmodule
// module dut;

//     reg clk = 0;
//     reg [31:0] address = `start_address;
//     wire [31:0] data_out;
//     reg [31:0] data_in = 0;
//     reg w_enable = 0;

   

//     initial begin


    
//         //$dumpfile("memory_testbench.vcd");
//             // All variables (0) from module instance gate
//             $dumpvars(0, mem1);
//             $dumpvars(0, dut);
            
//             #10 address = address + 4;
//             while(data_out != 0) #10 address = address + 4;

//         //    $display("Finished Reading the program");
//         //     #20 data_in = 32'hDEADBEEF;
//         //         w_enable = 1; $display("Driving a write to current address");
//         //     #10 w_enable = 0; $display("Deasserting write");
//         //     #10 address = address + 4;
//         //         data_in = 32'h00000001;
//         //         w_enable = 1;
//         //         #3 data_in = 32'h00000001;
//         //         #3 data_in = 32'h00000002;
//         //         #3 data_in = 32'h00000003;
//         //         #3 data_in = 32'h00000004;
//         //         #3 w_enable = 0;
//              #10 $finish;
//     end
    

//     memory mem1(.clk(clk),.address(address),.data_in(data_in),.w_enable(w_enable),.data_out(data_out));

//     always begin
//         #5 clk <= ~clk;
//     end

//     always @(posedge clk) begin
//        $display("TB: time=%t address=%x data_out(h)=%x, data_in(h)=%x , w_enable=%b", $time, address,data_out,data_in,w_enable);

//     end


// endmodule

PD2/Submission/Testbench_fetch_decode.v
`include "fetch_decode.v"
`include "constants.v"
`include "memory.v"

module dut;

    reg clk = 0;

    // instruction memmory inputs
    wire [31:0]next_PC;
    wire [31:0]i_mem_out;

    //Fetch_decoder inputs
    wire [31:0]instruction;
    wire [6:0]opcode;
    wire [4:0]rd;
    wire [2:0]funct3;
    wire [6:0]funct7;
    wire [4:0]rs1;
    wire [4:0]rs2;
    wire [4:0]shamt;
    wire signed [31:0]imm;
    wire rs1_en, rs2_en, rd_en, imm_e;
    wire [31:0] PC;

    initial begin
        $dumpfile("TB_fetch_decode.vcd");
        $dumpvars(0, dut);

    end

    always@(posedge clk) if(i_mem_out == 32'd0) begin
        #5$write("\n");
        $finish;

    end

    memory i_mem(.clk(clk),.address(next_PC),.data_in(32'd0),.w_enable(1'b0),.data_out(i_mem_out));

    //fetch_decode fd1(.clk(clk), instruction, opcode, rd, funct3, funct7, rs1, rs2, shamt, imm, rs1_en, rs2_en, rd_en, imm_e, PC);
    fetch_decode fd1(
            //inputs
            .clk(clk),
            .mem_out(i_mem_out),
            //outputs
            .next_PC(next_PC),
            .instruction(instruction),
            .opcode(opcode),
            .rd(rd),
            .funct3(funct3),
            .funct7(funct7),
            .rs1(rs1),
            .rs2(rs2),
            .shamt(rs2),
            .imm(imm),
            .rs1_en(rs1_en),
            .rs2_en(rs2_en),
            .rd_en(rd_en),
            .imm_e(imm_e),
            .PC(PC)
        );

    always begin
        #5 clk <= ~clk;
    end


    always@(posedge clk) begin
        //opcode determines instruction format, except for MCC types instructions (SLLI, SRLI, and SRAI are different than the other MCC instructions)
        $write("\nTB: current instruction components: opcode=%7b, func3=%3b, func7=%7b, rd=x%0d, rs1=x%0d, rs2=x%0d, imm=%0d\n", opcode, funct3, funct7, rd, rs1, rs2,imm);
       
        $write("%0x:  \t%8x    \t", PC, instruction);
        case(opcode)
            `LUI: begin
                $display("LUI    x%0d, 0x%0x", rd, imm);
            end
            `AUIPC: begin
                $display("AUIPC  x%0d, 0x%0x", rd, imm);
            end
            `JAL: begin
                $display("JAL    x%0d, %0x", rd, PC+imm);
            end
            `JALR: begin
                if (funct3 == 3'b000) begin
                    $display("JALR   x%0d, %0d(x%0d)", rd, imm,rs1);
                end
                else $display("Unknown function:%0b of Type JALR");
            end
            `BCC: begin
                case(funct3)
                    3'b000: $display("BEQ    x%0d, x%0d, %0x", rs1, rs2, PC+imm);
                    3'b001: $display("BNE    x%0d, x%0d, %0x", rs1, rs2, PC+imm);
                    3'b100: $display("BLT    x%0d, x%0d, %0x", rs1, rs2, PC+imm);
                    3'b101: $display("BGE    x%0d, x%0d, %0x", rs1, rs2, PC+imm);
                    3'b110: $display("BLTU   x%0d, x%0d, %0x", rs1, rs2, PC+imm);
                    3'b111: $display("BGEU    x%0d, x%0d, %0x", rs1, rs2,PC+imm);
                    default: $display("Unknown BCC Type: %0b", funct3);
                endcase
            end
            `LCC: begin
                case(funct3)
                    3'b000: $display("LB     %0d(x%0d)", rd, imm, rs1);
                    3'b001: $display("LH     x%0d, %0d(x%0d)", rd, imm, rs1);
                    3'b010: $display("LW     x%0d, %0d(x%0d)", rd, imm, rs1);
                    3'b100: $display("LBU    x%0d, %0d(x%0d)", rd, imm, rs1);
                    3'b101: $display("LHU    x%0d, %0d(x%0d)", rd, imm, rs1);
                    default: $display("Unknown LCC Type: %0b", funct3);
                endcase
            end
            `SCC: begin
                case(funct3)
                    3'b000: $display("SB     x%0d, %0d(x%0d)", rs2, imm, rs1);
                    3'b001: $display("SH     x%0d, %0d(x%0d)", rs2, imm, rs1);
                    3'b010: $display("SW     x%0d, %0d(x%0d)", rs2, imm, rs1);
                    default: $display("Unknown SCC Type: %0b", funct3);
                endcase
            end
            //we will always want to sign extend in MCC opcodes
            `MCC: begin
                case(funct3)
                    //I-Type cases
                    3'b000: $display("ADDI   x%0d, x%0d, %0d", rd, rs1, imm);
                    3'b010: $display("SLTI   x%0d, x%0d, %0d", rd, rs1, imm);
                    3'b011: $display("SLTIU  x%0d, x%0d, %0d", rd, rs1, imm);
                    3'b100: $display("XORI   x%0d, x%0d, %0d", rd, rs1, imm);
                    3'b110: $display("ORI    x%0d, x%0d, %0d", rd, rs1, imm);
                    3'b111: $display("ANDI   x%0d, x%0d, %0d", rd, rs1, imm);
                    //R-Type cases
                    3'b001: $display("SLLI   x%0d, x%0d, 0x%0x", rd, rs1, shamt);
                    3'b101: begin
                        case(funct7)
                            7'b0000000: $display("SRLI     x%0d,, %0d ,%0d)", rd, rs1, shamt);
                            7'b0100000: $display("SRAI     x%0d, %0d ,x%0d)", rd, rs1, shamt);
                            default: $display("Unknown MCC shift variant (%b) under funt3=101", funct7); 
                        endcase
                    end
                    default: $display("Unknown MCC opcode: %b", opcode);
                endcase
                
            end
            `RCC: begin
                case(funct3)
                    3'b000:begin
                        case(funct7)
                            7'b0000000: $display("ADD    x%0d, x%0d, x%0d", rd, rs1, rs2);
                            7'b0100000: $display("SUB    x%0d, x%0d, x%0d", rd, rs1, rs2);
                            default: $display("Unknown RCC shift variant (%b) under funt3=000", funct7); 
                        endcase
                    end
                    3'b001: $display("SLL    x%0d, x%0d, x%0d", rd, rs1, rs2);
                    3'b010: $display("SLT    x%0d, x%0d, x%0d", rd, rs1, rs2);
                    3'b011: $display("SLTU   x%0d, x%0d, x%0d", rd, rs1, rs2);
                    3'b100: $display("XOR    x%0d, x%0d, x%0d", rd, rs1, rs2);
                    3'b101:begin
                        case(funct7)
                            7'b0000000: $display("SRL     x%0d,, %0d ,%0d)", rd, rs1, shamt);
                            7'b0100000: $display("SRA     x%0d, %0d ,%0d)", rd, rs1, shamt);
                            default: $display("Unknown RCC shift variant (%b) under funct3=101", funct7); 
                        endcase
                    end
                    3'b110: $display("OR     x%0d, x%0d, x%0d", rd, rs1, rs2);
                    3'b111: $display("AND    x%0d, x%0d, x%0d", rd, rs1, rs2);
                endcase
            end
            `FCC: begin
                $write("Detected a FCC opcode, these are not implemented\n");
            end
            `CCC: begin
                //$write("Detected a CCC opcode\n");
                if(instruction[31:7] == 25'd0) $display("ECALL  ");
                else $display("Looks an ECALL but doesn't match what I expected: %b", instruction);

            end
            default: $display(" error");


        endcase


    end








endmodule

PD2/TB_fetch_decode.vcd
$date
	Wed Jun  3 22:49:01 2020
$end
$version
	Icarus Verilog
$end
$timescale
	1s
$end
$scope module dut $end
$var wire 5 ! rs2 [4:0] $end
$var wire 5 " shamt [4:0] $end
$var wire 1 # rs2_en $end
$var wire 1 $ rs1_en $end
$var wire 5 % rs1 [4:0] $end
$var wire 1 & rd_en $end
$var wire 5 ' rd [4:0] $end
$var wire 7 ( opcode [6:0] $end
$var wire 32 ) next_PC [31:0] $end
$var wire 32 * instruction [31:0] $end
$var wire 1 + imm_e $end
$var wire 32 , imm [31:0] $end
$var wire 32 - i_mem_out [31:0] $end
$var wire 7 . funct7 [6:0] $end
$var wire 3 / funct3 [2:0] $end
$var wire 32 0 PC [31:0] $end
$var reg 1 1 clk $end
$scope module fd1 $end
$var wire 1 1 clk $end
$var wire 5 2 rs2 [4:0] $end
$var wire 5 3 shamt [4:0] $end
$var wire 5 4 rs1 [4:0] $end
$var wire 5 5 rd [4:0] $end
$var wire 7 6 opcode [6:0] $end
$var wire 32 7 mem_out [31:0] $end
$var wire 7 8 funct7 [6:0] $end
$var wire 3 9 funct3 [2:0] $end
$var reg 32 : PC [31:0] $end
$var reg 32 ; imm [31:0] $end
$var reg 1 + imm_e $end
$var reg 32 < instruction [31:0] $end
$var reg 32 = next_PC [31:0] $end
$var reg 1 & rd_en $end
$var reg 1 $ rs1_en $end
$var reg 1 # rs2_en $end
$scope task decode_bType $end
$upscope $end
$scope task decode_iType $end
$upscope $end
$scope task decode_jType $end
$upscope $end
$scope task decode_rType $end
$upscope $end
$scope task decode_sType $end
$upscope $end
$scope task decode_uType $end
$upscope $end
$upscope $end
$scope module i_mem $end
$var wire 32 > address [31:0] $end
$var wire 1 1 clk $end
$var wire 32 ? data_in [31:0] $end
$var wire 1 @ w_enable $end
$var reg 32 A data_out [31:0] $end
$var reg 32 B t_reg [31:0] $end
$var integer 32 C i [31:0] $end
$upscope $end
$upscope $end
$enddefinitions $end
#0
$dumpvars
b100000000000000000001 C
bx B
b11111100000000010000000100010011 A
0@
b0 ?
b1000000000000000000000000 >
b1000000000000000000000000 =
bx <
bx ;
bx :
bx 9
bx 8
b11111100000000010000000100010011 7
bx 6
bx 5
bx 4
bx 3
bx 2
01
bx 0
bx /
bx .
b11111100000000010000000100010011 -
bx ,
x+
bx *
b1000000000000000000000000 )
bx (
bx '
x&
bx %
x$
x#
bz "
bx !
$end
#5
b10000100010010111000100011 -
b10000100010010111000100011 7
b10000100010010111000100011 A
b11111111111111111111111111000000 ,
b11111111111111111111111111000000 ;
1+
0#
1$
1&
b10011 (
b10011 6
b10 '
b10 5
b0 /
b0 9
b10 %
b10 4
b0 !
b0 2
b0 3
b1111110 .
b1111110 8
b1000000000000000000000100 )
b1000000000000000000000100 =
b1000000000000000000000100 >
b1000000000000000000000000 0
b1000000000000000000000000 :
b11111100000000010000000100010011 *
b11111100000000010000000100010011 <
11
#10
01
#15
b10000000010010011000100011 -
b10000000010010011000100011 7
b10000000010010011000100011 A
b111100 ,
b111100 ;
1#
0&
b100011 (
b100011 6
b11100 '
b11100 5
b10 /
b10 9
b1 .
b1 8
b1 !
b1 2
b1 3
b1000000000000000000001000 )
b1000000000000000000001000 =
b1000000000000000000001000 >
b1000000000000000000000100 0
b1000000000000000000000100 :
b10000100010010111000100011 *
b10000100010010111000100011 <
11
#20
01
#25
b10000000010010010000100011 -
b10000000010010010000100011 7
b10000000010010010000100011 A
b101100 ,
b101100 ;
b1100 '
b1100 5
b0 !
b0 2
b0 3
b1000000000000000000001100 )
b1000000000000000000001100 =
b1000000000000000000001100 >
b1000000000000000000001000 0
b1000000000000000000001000 :
b10000000010010011000100011 *
b10000000010010011000100011 <
11
#30
01
#35
b10000000010010011000100011 -
b10000000010010011000100011 7
b10000000010010011000100011 A
b101000 ,
b101000 ;
b1000 '
b1000 5
b1000000000000000000010000 )
b1000000000000000000010000 =
b1000000000000000000010000 >
b1000000000000000000001100 0
b1000000000000000000001100 :
b10000000010010010000100011 *
b10000000010010010000100011 <
11
#40
01
#45
b10100000000000000001101111 -
b10100000000000000001101111 7
b10100000000000000001101111 A
b101100 ,
b101100 ;
b1100 '
b1100 5
b1000000000000000000010100 )
b1000000000000000000010100 =
b1000000000000000000010100 >
b1000000000000000000010000 0
b1000000000000000000010000 :
b10000000010010011000100011 *
b10000000010010011000100011 <
11
#50
01
#55
b10110000010010011110000011 -
b10110000010010011110000011 7
b10110000010010011110000011 A
b101000 ,
b101000 ;
0#
0$
1&
b1101111 (
b1101111 6
b0 '
b0 5
b0 /
b0 9
b0 %
b0 4
b1000 !
b1000 2
b1000 3
b1000000000000000000011000 )
b1000000000000000000011000 =
b1000000000000000000011000 >
b1000000000000000000010100 0
b1000000000000000000010100 :
b10100000000000000001101111 *
b10100000000000000001101111 <
11
#60
01
#65
b1001111001011110010011 -
b1001111001011110010011 7
b1001111001011110010011 A
b101100 ,
b101100 ;
1$
b11 (
b11 6
b1111 '
b1111 5
b10 /
b10 9
b10 %
b10 4
b1100 !
b1100 2
b1100 3
b1000000000000000000011100 )
b1000000000000000000011100 =
b1000000000000000000011100 >
b1000000000000000000011000 0
b1000000000000000000011000 :
b10110000010010011110000011 *
b10110000010010011110000011 <
11
#70
01
#75
b11000000010000011100010011 -
b11000000010000011100010011 7
b11000000010000011100010011 A
0+
1#
b10011 (
b10011 6
b1 /
b1 9
b1111 %
b1111 4
b0 .
b0 8
b10 !
b10 2
b10 3
b1000000000000000000100000 )
b1000000000000000000100000 =
b1000000000000000000100000 >
b1000000000000000000011100 0
b1000000000000000000011100 :
b1001111001011110010011 *
b1001111001011110010011 <
11
#80
01
#85
b111101110000011110110011 -
b111101110000011110110011 7
b111101110000011110110011 A
b110000 ,
b110000 ;
1+
0#
b1110 '
b1110 5
b0 /
b0 9
b10 %
b10 4
b1 .
b1 8
b10000 !
b10000 2
b10000 3
b1000000000000000000100100 )
b1000000000000000000100100 =
b1000000000000000000100100 >
b1000000000000000000100000 0
b1000000000000000000100000 :
b11000000010000011100010011 *
b11000000010000011100010011 <
11
#90
01
#95
b10110000010010011100000011 -
b10110000010010011100000011 7
b10110000010010011100000011 A
0+
1#
b110011 (
b110011 6
b1111 '
b1111 5
b1110 %
b1110 4
b0 .
b0 8
b1111 !
b1111 2
b1111 3
b1000000000000000000101000 )
b1000000000000000000101000 =
b1000000000000000000101000 >
b1000000000000000000100100 0
b1000000000000000000100100 :
b111101110000011110110011 *
b111101110000011110110011 <
11
#100
01
#105
b11111100111001111010100000100011 -
b11111100111001111010100000100011 7
b11111100111001111010100000100011 A
b101100 ,
b101100 ;
1+
0#
b11 (
b11 6
b1110 '
b1110 5
b10 /
b10 9
b10 %
b10 4
b1 .
b1 8
b1100 !
b1100 2
b1100 3
b1000000000000000000101100 )
b1000000000000000000101100 =
b1000000000000000000101100 >
b1000000000000000000101000 0
b1000000000000000000101000 :
b10110000010010011100000011 *
b10110000010010011100000011 <
11
#110
01
#115
b10110000010010011110000011 -
b10110000010010011110000011 7
b10110000010010011110000011 A
b11111111111111111111111111010000 ,
b11111111111111111111111111010000 ;
1#
0&
b100011 (
b100011 6
b10000 '
b10000 5
b1111 %
b1111 4
b1111110 .
b1111110 8
b1110 !
b1110 2
b1110 3
b1000000000000000000110000 )
b1000000000000000000110000 =
b1000000000000000000110000 >
b1000000000000000000101100 0
b1000000000000000000101100 :
b11111100111001111010100000100011 *
b11111100111001111010100000100011 <
11
#120
01
#125
b101111000011110010011 -
b101111000011110010011 7
b101111000011110010011 A
b101100 ,
b101100 ;
0#
1&
b11 (
b11 6
b1111 '
b1111 5
b10 %
b10 4
b1 .
b1 8
b1100 !
b1100 2
b1100 3
b1000000000000000000110100 )
b1000000000000000000110100 =
b1000000000000000000110100 >
b1000000000000000000110000 0
b1000000000000000000110000 :
b10110000010010011110000011 *
b10110000010010011110000011 <
11
#130
01
#135
b10111100010010011000100011 -
b10111100010010011000100011 7
b10111100010010011000100011 A
b1 ,
b1 ;
b10011 (
b10011 6
b0 /
b0 9
b1111 %
b1111 4
b0 .
b0 8
b1 !
b1 2
b1 3
b1000000000000000000111000 )
b1000000000000000000111000 =
b1000000000000000000111000 >
b1000000000000000000110100 0
b1000000000000000000110100 :
b101111000011110010011 *
b101111000011110010011 <
11
#140
01
#145
b10110000010010011100000011 -
b10110000010010011100000011 7
b10110000010010011100000011 A
b101100 ,
b101100 ;
1#
0&
b100011 (
b100011 6
b1100 '
b1100 5
b10 /
b10 9
b10 %
b10 4
b1 .
b1 8
b1111 !
b1111 2
b1111 3
b1000000000000000000111100 )
b1000000000000000000111100 =
b1000000000000000000111100 >
b1000000000000000000111000 0
b1000000000000000000111000 :
b10111100010010011000100011 *
b10111100010010011000100011 <
11
#150
01
#155
b100100000000011110010011 -
b100100000000011110010011 7
b100100000000011110010011 A
0#
1&
b11 (
b11 6
b1110 '
b1110 5
b1100 !
b1100 2
b1100 3
b1000000000000000001000000 )
b1000000000000000001000000 =
b1000000000000000001000000 >
b1000000000000000000111100 0
b1000000000000000000111100 :
b10110000010010011100000011 *
b10110000010010011100000011 <
11
#160
01
#165
b11111100111001111101101011100011 -
b11111100111001111101101011100011 7
b11111100111001111101101011100011 A
b1001 ,
b1001 ;
b10011 (
b10011 6
b1111 '
b1111 5
b0 /
b0 9
b0 %
b0 4
b0 .
b0 8
b1001 !
b1001 2
b1001 3
b1000000000000000001000100 )
b1000000000000000001000100 =
b1000000000000000001000100 >
b1000000000000000001000000 0
b1000000000000000001000000 :
b100100000000011110010011 *
b100100000000011110010011 <
11
#170
01
#175
b10000000010010011000100011 -
b10000000010010011000100011 7
b10000000010010011000100011 A
b11111111111111111111111111010100 ,
b11111111111111111111111111010100 ;
1#
0&
b1100011 (
b1100011 6
b10101 '
b10101 5
b101 /
b101 9
b1111 %
b1111 4
b1111110 .
b1111110 8
b1110 !
b1110 2
b1110 3
b1000000000000000001001000 )
b1000000000000000001001000 =
b1000000000000000001001000 >
b1000000000000000001000100 0
b1000000000000000001000100 :
b11111100111001111101101011100011 *
b11111100111001111101101011100011 <
11
#180
01
#185
b11000000000000000001101111 -
b11000000000000000001101111 7
b11000000000000000001101111 A
b101100 ,
b101100 ;
b100011 (
b100011 6
b1100 '
b1100 5
b10 /
b10 9
b10 %
b10 4
b1 .
b1 8
b0 !
b0 2
b0 3
b1000000000000000001001100 )
b1000000000000000001001100 =
b1000000000000000001001100 >
b1000000000000000001001000 0
b1000000000000000001001000 :
b10000000010010011000100011 *
b10000000010010011000100011 <
11
#190
01
#195
b10110000010010011110000011 -
b10110000010010011110000011 7
b10110000010010011110000011 A
b110000 ,
b110000 ;
0#
0$
1&
b1101111 (
b1101111 6
b0 '
b0 5
b0 /
b0 9
b0 %
b0 4
b10000 !
b10000 2
b10000 3
b1000000000000000001010000 )
b1000000000000000001010000 =
b1000000000000000001010000 >
b1000000000000000001001100 0
b1000000000000000001001100 :
b11000000000000000001101111 *
b11000000000000000001101111 <
11
#200
01
#205
b1001111001011110010011 -
b1001111001011110010011 7
b1001111001011110010011 A
b101100 ,
b101100 ;
1$
b11 (
b11 6
b1111 '
b1111 5
b10 /
b10 9
b10 %
b10 4
b1100 !
b1100 2
b1100 3
b1000000000000000001010100 )
b1000000000000000001010100 =
b1000000000000000001010100 >
b1000000000000000001010000 0
b1000000000000000001010000 :
b10110000010010011110000011 *
b10110000010010011110000011 <
11
#210
01
#215
b11000000010000011100010011 -
b11000000010000011100010011 7
b11000000010000011100010011 A
0+
1#
b10011 (
b10011 6
b1 /
b1 9
b1111 %
b1111 4
b0 .
b0 8
b10 !
b10 2
b10 3
b1000000000000000001011000 )
b1000000000000000001011000 =
b1000000000000000001011000 >
b1000000000000000001010100 0
b1000000000000000001010100 :
b1001111001011110010011 *
b1001111001011110010011 <
11
#220
01
#225
b111101110000011110110011 -
b111101110000011110110011 7
b111101110000011110110011 A
b110000 ,
b110000 ;
1+
0#
b1110 '
b1110 5
b0 /
b0 9
b10 %
b10 4
b1 .
b1 8
b10000 !
b10000 2
b10000 3
b1000000000000000001011100 )
b1000000000000000001011100 =
b1000000000000000001011100 >
b1000000000000000001011000 0
b1000000000000000001011000 :
b11000000010000011100010011 *
b11000000010000011100010011 <
11
#230
01
#235
b11111101000001111010011110000011 -
b11111101000001111010011110000011 7
b11111101000001111010011110000011 A
0+
1#
b110011 (
b110011 6
b1111 '
b1111 5
b1110 %
b1110 4
b0 .
b0 8
b1111 !
b1111 2
b1111 3
b1000000000000000001100000 )
b1000000000000000001100000 =
b1000000000000000001100000 >
b1000000000000000001011100 0
b1000000000000000001011100 :
b111101110000011110110011 *
b111101110000011110110011 <
11
#240
01
#245
b10100000010010011100000011 -
b10100000010010011100000011 7
b10100000010010011100000011 A
b11111111111111111111111111010000 ,
b11111111111111111111111111010000 ;
1+
0#
b11 (
b11 6
b10 /
b10 9
b1111 %
b1111 4
b1111110 .
b1111110 8
b10000 !
b10000 2
b10000 3
b1000000000000000001100100 )
b1000000000000000001100100 =
b1000000000000000001100100 >
b1000000000000000001100000 0
b1000000000000000001100000 :
b11111101000001111010011110000011 *
b11111101000001111010011110000011 <
11
#250
01
#255
b111101110000011110110011 -
b111101110000011110110011 7
b111101110000011110110011 A
b101000 ,
b101000 ;
b1110 '
b1110 5
b10 %
b10 4
b1 .
b1 8
b1000 !
b1000 2
b1000 3
b1000000000000000001101000 )
b1000000000000000001101000 =
b1000000000000000001101000 >
b1000000000000000001100100 0
b1000000000000000001100100 :
b10100000010010011100000011 *
b10100000010010011100000011 <
11
#260
01
#265
b10111100010010010000100011 -
b10111100010010010000100011 7
b10111100010010010000100011 A
0+
1#
b110011 (
b110011 6
b1111 '
b1111 5
b0 /
b0 9
b1110 %
b1110 4
b0 .
b0 8
b1111 !
b1111 2
b1111 3
b1000000000000000001101100 )
b1000000000000000001101100 =
b1000000000000000001101100 >
b1000000000000000001101000 0
b1000000000000000001101000 :
b111101110000011110110011 *
b111101110000011110110011 <
11
#270
01
#275
b10110000010010011110000011 -
b10110000010010011110000011 7
b10110000010010011110000011 A
1+
0&
b100011 (
b100011 6
b1000 '
b1000 5
b10 /
b10 9
b10 %
b10 4
b1 .
b1 8
b1000000000000000001110000 )
b1000000000000000001110000 =
b1000000000000000001110000 >
b1000000000000000001101100 0
b1000000000000000001101100 :
b10111100010010010000100011 *
b10111100010010010000100011 <
11
#280
01
#285
b101111000011110010011 -
b101111000011110010011 7
b101111000011110010011 A
b101100 ,
b101100 ;
0#
1&
b11 (
b11 6
b1111 '
b1111 5
b1100 !
b1100 2
b1100 3
b1000000000000000001110100 )
b1000000000000000001110100 =
b1000000000000000001110100 >
b1000000000000000001110000 0
b1000000000000000001110000 :
b10110000010010011110000011 *
b10110000010010011110000011 <
11
#290
01
#295
b10111100010010011000100011 -
b10111100010010011000100011 7
b10111100010010011000100011 A
b1 ,
b1 ;
b10011 (
b10011 6
b0 /
b0 9
b1111 %
b1111 4
b0 .
b0 8
b1 !
b1 2
b1 3
b1000000000000000001111000 )
b1000000000000000001111000 =
b1000000000000000001111000 >
b1000000000000000001110100 0
b1000000000000000001110100 :
b101111000011110010011 *
b101111000011110010011 <
11
#300
01
#305
b10110000010010011100000011 -
b10110000010010011100000011 7
b10110000010010011100000011 A
b101100 ,
b101100 ;
1#
0&
b100011 (
b100011 6
b1100 '
b1100 5
b10 /
b10 9
b10 %
b10 4
b1 .
b1 8
b1111 !
b1111 2
b1111 3
b1000000000000000001111100 )
b1000000000000000001111100 =
b1000000000000000001111100 >
b1000000000000000001111000 0
b1000000000000000001111000 :
b10111100010010011000100011 *
b10111100010010011000100011 <
11
#310
01
